lins_dbmanagers/__init__.py
lins_dbmanagers/prefetch.py
lins_dbmanagers-0.1.0.2.dist-info/METADATA
lins_dbmanagers-0.1.0.2.dist-info/WHEEL
lins_dbmanagers-0.1.0.2.dist-info/top_level.txt
lins_dbmanagers-0.1.0.2.dist-info/RECORD
