Metadata-Version: 2.1
Name: lins-dbmanagers
Version: 0.1.0.2
Summary: Managers com funcionalidades extras para os models Django.
Home-page: https://bitbucket.org/grupolinsferrao/pypck-lins_dbmanagers/
Author: Lucas Lehnen
Author-email: lucas@lojaspompeia.com.br
License: MIT
Platform: UNKNOWN
